NiukeWangMingqiXiaozhaoBishiZhentiJingxuanJishuPian20202021Fix1/README.md
NiukeWangMingqiXiaozhaoBishiZhentiJingxuanJishuPian20202021Fix1/__init__.py
NiukeWangMingqiXiaozhaoBishiZhentiJingxuanJishuPian20202021Fix1/__main__.py
NiukeWangMingqiXiaozhaoBishiZhentiJingxuanJishuPian20202021Fix1/file.epub
NiukeWangMingqiXiaozhaoBishiZhentiJingxuanJishuPian20202021Fix1/index.html
NiukeWangMingqiXiaozhaoBishiZhentiJingxuanJishuPian20202021Fix1/css/__init__.py
NiukeWangMingqiXiaozhaoBishiZhentiJingxuanJishuPian20202021Fix1/css/annotations.css
NiukeWangMingqiXiaozhaoBishiZhentiJingxuanJishuPian20202021Fix1/css/main.css
NiukeWangMingqiXiaozhaoBishiZhentiJingxuanJishuPian20202021Fix1/css/normalize.css
NiukeWangMingqiXiaozhaoBishiZhentiJingxuanJishuPian20202021Fix1/css/popup.css
NiukeWangMingqiXiaozhaoBishiZhentiJingxuanJishuPian20202021Fix1/font/__init__.py
NiukeWangMingqiXiaozhaoBishiZhentiJingxuanJishuPian20202021Fix1/font/fontello.eot
NiukeWangMingqiXiaozhaoBishiZhentiJingxuanJishuPian20202021Fix1/font/fontello.svg
NiukeWangMingqiXiaozhaoBishiZhentiJingxuanJishuPian20202021Fix1/font/fontello.ttf
NiukeWangMingqiXiaozhaoBishiZhentiJingxuanJishuPian20202021Fix1/font/fontello.woff
NiukeWangMingqiXiaozhaoBishiZhentiJingxuanJishuPian20202021Fix1/img/__init__.py
NiukeWangMingqiXiaozhaoBishiZhentiJingxuanJishuPian20202021Fix1/img/annotator-glyph-sprite.png
NiukeWangMingqiXiaozhaoBishiZhentiJingxuanJishuPian20202021Fix1/img/annotator-icon-sprite.png
NiukeWangMingqiXiaozhaoBishiZhentiJingxuanJishuPian20202021Fix1/img/apple-touch-icon.png
NiukeWangMingqiXiaozhaoBishiZhentiJingxuanJishuPian20202021Fix1/img/cancelfullscreen.png
NiukeWangMingqiXiaozhaoBishiZhentiJingxuanJishuPian20202021Fix1/img/close.png
NiukeWangMingqiXiaozhaoBishiZhentiJingxuanJishuPian20202021Fix1/img/fullscreen.png
NiukeWangMingqiXiaozhaoBishiZhentiJingxuanJishuPian20202021Fix1/img/loader.gif
NiukeWangMingqiXiaozhaoBishiZhentiJingxuanJishuPian20202021Fix1/img/menu-icon.png
niuke_wang_mingqi_xiaozhao_bishi_zhenti_jingxuan_jishu_pian_2020_2021_fix1-2025.3.24.0.dist-info/METADATA
niuke_wang_mingqi_xiaozhao_bishi_zhenti_jingxuan_jishu_pian_2020_2021_fix1-2025.3.24.0.dist-info/WHEEL
niuke_wang_mingqi_xiaozhao_bishi_zhenti_jingxuan_jishu_pian_2020_2021_fix1-2025.3.24.0.dist-info/entry_points.txt
niuke_wang_mingqi_xiaozhao_bishi_zhenti_jingxuan_jishu_pian_2020_2021_fix1-2025.3.24.0.dist-info/top_level.txt
niuke_wang_mingqi_xiaozhao_bishi_zhenti_jingxuan_jishu_pian_2020_2021_fix1-2025.3.24.0.dist-info/RECORD
